Metadata-Version: 2.3
Name: martian-adapters
Version: 7.25.0
Summary: Adapters as API gateways to Different LLM Models
Author: Martian team
Author-email: team@withmartian.com
Requires-Python: >=3.11,<4.0
Classifier: Programming Language :: Python :: 3
Classifier: Programming Language :: Python :: 3.11
Classifier: Programming Language :: Python :: 3.12
Classifier: Programming Language :: Python :: 3.13
Requires-Dist: anthropic (>=0.49.0,<0.50.0)
Requires-Dist: brotli (>=1.1.0,<2.0.0)
Requires-Dist: cohere (>=5.14.0,<6.0.0)
Requires-Dist: httpx[http2] (>=0.28.1,<0.29.0)
Requires-Dist: openai (>=1.68.2,<2.0.0)
Requires-Dist: pydantic (>=2.9.2,<3.0.0)
